{"count":58808,"next":"http://129.241.150.113:8000/books/?languages=en&page=462","previous":"http://129.241.150.113:8000/books/?languages=en&page=460","results":[{"id":43797,"title":"Favorite Fish and Fishing","authors":[{"name":"Henshall, James A. (James Alexander)","birth_year":1836,"death_year":1925}],"translators":[],"subjects":["Fishes -- North America","Fishing -- North America"],"bookshelves":[],"languages":["en"],"copyright":false,"media_type":"Text","formats":{"text/html":"https://www.gutenberg.org/ebooks/43797.html.images","text/html; charset=iso-8859-1":"https://www.gutenberg.org/files/43797/43797-h/43797-h.htm","application/epub+zip":"https://www.gutenberg.org/ebooks/43797.epub3.images","application/x-mobipocket-ebook":"https://www.gutenberg.org/ebooks/43797.kf8.images","text/plain; charset=us-ascii":"https://www.gutenberg.org/ebooks/43797.txt.utf-8","text/plain; charset=utf-8":"https://www.gutenberg.org/files/43797/43797-0.txt","text/plain; charset=iso-8859-1":"https://www.gutenberg.org/files/43797/43797-8.txt","application/rdf+xml":"https://www.gutenberg.org/ebooks/43797.rdf","image/jpeg":"https://www.gutenberg.org/cache/epub/43797/pg43797.cover.medium.jpg","application/octet-stream":"https://www.gutenberg.org/cache/epub/43797/pg43797-h.zip"},"download_count":65},{"id":44303,"title":"A Chambermaid's Diary","authors":[{"name":"Mirbeau, Octave","birth_year":1848,"death_year":1917}],"translators":[{"name":"Tucker, Benjamin Ricketson","birth_year":1854,"death_year":1939}],"subjects":["French fiction -- Translations into English"],"bookshelves":[],"languages":["en"],"copyright":false,"media_type":"Text","formats":{"text/html":"https://www.gutenberg.org/ebooks/44303.html.images","text/html; charset=iso-8859-1":"https://www.gutenberg.org/files/44303/44303-h/44303-h.htm","application/epub+zip":"https://www.gutenberg.org/ebooks/44303.epub3.images","application/x-mobipocket-ebook":"https://www.gutenberg.org/ebooks/44303.kf8.images","text/plain; charset=us-ascii":"https://www.gutenberg.org/ebooks/44303.txt.utf-8","text/plain; charset=iso-8859-1":"https://www.gutenberg.org/files/44303/44303-8.txt","application/rdf+xml":"https://www.gutenberg.org/ebooks/44303.rdf","image/jpeg":"https://www.gutenberg.org/cache/epub/44303/pg44303.cover.medium.jpg","application/octet-stream":"https://www.gutenberg.org/cache/epub/44303/pg44303-h.zip"},"download_count":65},{"id":44493,"title":"History of Civilization in England,  Vol. 1 of 3","authors":[{"name":"Buckle, Henry Thomas","birth_year":1821,"death_year":1862}],"translators":[],"subjects":["Civilization -- History","England -- Civilization","France -- Civilization","Great Britain -- Civilization","Scotland -- History","Spain -- Civilization"],"bookshelves":[],"languages":["en"],"copyright":false,"media_type":"Text","formats":{"text/html":"https://www.gutenberg.org/ebooks/44493.html.images","text/html; charset=iso-8859-1":"https://www.gutenberg.org/files/44493/44493-h/44493-h.htm","application/epub+zip":"https://www.gutenberg.org/ebooks/44493.epub3.images","application/x-mobipocket-ebook":"https://www.gutenberg.org/ebooks/44493.kf8.images","text/plain; charset=us-ascii":"https://www.gutenberg.org/ebooks/44493.txt.utf-8","text/plain; charset=iso-8859-1":"https://www.gutenberg.org/files/44493/44493-8.txt","application/rdf+xml":"https://www.gutenberg.org/ebooks/44493.rdf","image/jpeg":"https://www.gutenberg.org/cache/epub/44493/pg44493.cover.medium.jpg","application/octet-stream":"https://www.gutenberg.org/cache/epub/44493/pg44493-h.zip"},"download_count":65},{"id":44841,"title":"The Mark of Cain","authors":[{"name":"Wells, Carolyn","birth_year":1862,"death_year":1942}],"translators":[],"subjects":["Detective and mystery stories","Fiction"],"bookshelves":[],"languages":["en"],"copyright":false,"media_type":"Text","formats":{"text/html":"https://www.gutenberg.org/ebooks/44841.html.images","text/html; charset=utf-8":"https://www.gutenberg.org/files/44841/44841-h/44841-h.htm","application/epub+zip":"https://www.gutenberg.org/ebooks/44841.epub3.images","application/x-mobipocket-ebook":"https://www.gutenberg.org/ebooks/44841.kf8.images","text/plain; charset=us-ascii":"https://www.gutenberg.org/ebooks/44841.txt.utf-8","text/plain; charset=utf-8":"https://www.gutenberg.org/files/44841/44841-0.txt","text/plain; charset=iso-8859-1":"https://www.gutenberg.org/files/44841/44841-8.txt","application/rdf+xml":"https://www.gutenberg.org/ebooks/44841.rdf","image/jpeg":"https://www.gutenberg.org/cache/epub/44841/pg44841.cover.medium.jpg","application/octet-stream":"https://www.gutenberg.org/cache/epub/44841/pg44841-h.zip"},"download_count":65},{"id":45129,"title":"The History, Theory, and Practice of Illuminating: Condensed from 'The Art of Illuminating' by the same illustrator and author","authors":[{"name":"Wyatt, M. Digby (Matthew Digby), Sir","birth_year":1820,"death_year":1877}],"translators":[],"subjects":["Alphabet","Illumination of books and manuscripts","Initials"],"bookshelves":[],"languages":["en"],"copyright":false,"media_type":"Text","formats":{"text/html":"https://www.gutenberg.org/ebooks/45129.html.images","text/html; charset=iso-8859-1":"https://www.gutenberg.org/files/45129/45129-h/45129-h.htm","application/epub+zip":"https://www.gutenberg.org/ebooks/45129.epub3.images","application/x-mobipocket-ebook":"https://www.gutenberg.org/ebooks/45129.kf8.images","text/plain; charset=us-ascii":"https://www.gutenberg.org/ebooks/45129.txt.utf-8","text/plain; charset=iso-8859-1":"https://www.gutenberg.org/files/45129/45129-8.txt","application/rdf+xml":"https://www.gutenberg.org/ebooks/45129.rdf","image/jpeg":"https://www.gutenberg.org/cache/epub/45129/pg45129.cover.medium.jpg","application/octet-stream":"https://www.gutenberg.org/cache/epub/45129/pg45129-h.zip"},"download_count":65},{"id":45141,"title":"Pirates' Hope","authors":[{"name":"Lynde, Francis","birth_year":1856,"death_year":1930}],"translators":[],"subjects":["Caribbean Sea -- Fiction","Castaways -- Fiction","Islands -- Fiction","Pirates -- Fiction","Treasure troves -- Fiction","Yachting -- Fiction"],"bookshelves":[],"languages":["en"],"copyright":false,"media_type":"Text","formats":{"text/html":"https://www.gutenberg.org/ebooks/45141.html.images","text/html; charset=iso-8859-1":"https://www.gutenberg.org/files/45141/45141-h/45141-h.htm","application/epub+zip":"https://www.gutenberg.org/ebooks/45141.epub3.images","application/x-mobipocket-ebook":"https://www.gutenberg.org/ebooks/45141.kf8.images","text/plain; charset=us-ascii":"https://www.gutenberg.org/ebooks/45141.txt.utf-8","text/plain; charset=iso-8859-1":"https://www.gutenberg.org/files/45141/45141-8.txt","application/rdf+xml":"https://www.gutenberg.org/ebooks/45141.rdf","image/jpeg":"https://www.gutenberg.org/cache/epub/45141/pg45141.cover.medium.jpg","application/octet-stream":"https://www.gutenberg.org/cache/epub/45141/pg45141-h.zip"},"download_count":65},{"id":45442,"title":"A Camera Actress in the Wilds of Togoland: The adventures, observations & experiences of a cinematograph actress in West African forests whilst collecting films depicting native life and when posing as the white woman in Anglo-African cinematograph dramas","authors":[{"name":"Gehrts, Meg","birth_year":1891,"death_year":1966}],"translators":[],"subjects":["Togo -- Description and travel","Togoland -- Description and travel"],"bookshelves":[],"languages":["en"],"copyright":false,"media_type":"Text","formats":{"text/html":"https://www.gutenberg.org/ebooks/45442.html.images","text/html; charset=iso-8859-1":"https://www.gutenberg.org/files/45442/45442-h/45442-h.htm","application/epub+zip":"https://www.gutenberg.org/ebooks/45442.epub3.images","application/x-mobipocket-ebook":"https://www.gutenberg.org/ebooks/45442.kf8.images","text/plain; charset=us-ascii":"https://www.gutenberg.org/ebooks/45442.txt.utf-8","text/plain; charset=iso-8859-1":"https://www.gutenberg.org/files/45442/45442-8.txt","application/rdf+xml":"https://www.gutenberg.org/ebooks/45442.rdf","image/jpeg":"https://www.gutenberg.org/cache/epub/45442/pg45442.cover.medium.jpg","application/octet-stream":"https://www.gutenberg.org/cache/epub/45442/pg45442-h.zip"},"download_count":65},{"id":45542,"title":"Eighteen months in the war zone : $b the record of a woman's work on the western front","authors":[{"name":"Finzi, Kate John","birth_year":1890,"death_year":1958}],"translators":[],"subjects":["Finzi, Kate John, 1890-1958","World War, 1914-1918 -- Hospitals","World War, 1914-1918 -- Hospitals -- France -- Boulogne-sur-Mer","World War, 1914-1918 -- Personal narratives","World War, 1914-1918 -- Personal narratives, British","World War, 1914-1918 -- Women -- Great Britain"],"bookshelves":["Women's Travel Journals","World War I"],"languages":["en"],"copyright":false,"media_type":"Text","formats":{"text/html":"https://www.gutenberg.org/ebooks/45542.html.images","text/html; charset=us-ascii":"https://www.gutenberg.org/files/45542/45542-h/45542-h.htm","application/epub+zip":"https://www.gutenberg.org/ebooks/45542.epub3.images","application/x-mobipocket-ebook":"https://www.gutenberg.org/ebooks/45542.kf8.images","text/plain; charset=us-ascii":"https://www.gutenberg.org/ebooks/45542.txt.utf-8","text/plain; charset=iso-8859-1":"https://www.gutenberg.org/files/45542/45542-8.txt","application/rdf+xml":"https://www.gutenberg.org/ebooks/45542.rdf","image/jpeg":"https://www.gutenberg.org/cache/epub/45542/pg45542.cover.medium.jpg","application/octet-stream":"https://www.gutenberg.org/cache/epub/45542/pg45542-h.zip"},"download_count":65},{"id":45621,"title":"South America To-day: A Study of Conditions, Social, Political and Commercial in Argentina, Uruguay and Brazil","authors":[{"name":"Clemenceau, Georges","birth_year":1841,"death_year":1929}],"translators":[],"subjects":["Argentina -- Description and travel","Brazil -- Description and travel","South America -- Description and travel","Uruguay -- Description and travel"],"bookshelves":[],"languages":["en"],"copyright":false,"media_type":"Text","formats":{"text/html":"https://www.gutenberg.org/ebooks/45621.html.images","application/epub+zip":"https://www.gutenberg.org/ebooks/45621.epub3.images","application/x-mobipocket-ebook":"https://www.gutenberg.org/ebooks/45621.kf8.images","text/plain; charset=us-ascii":"https://www.gutenberg.org/ebooks/45621.txt.utf-8","text/plain; charset=iso-8859-1":"https://www.gutenberg.org/files/45621/45621-8.txt","application/rdf+xml":"https://www.gutenberg.org/ebooks/45621.rdf","image/jpeg":"https://www.gutenberg.org/cache/epub/45621/pg45621.cover.medium.jpg","application/octet-stream":"https://www.gutenberg.org/cache/epub/45621/pg45621-h.zip"},"download_count":65},{"id":45677,"title":"Popular Amusements","authors":[{"name":"Crane, J. T. (Jonathan Townley)","birth_year":1819,"death_year":1880}],"translators":[],"subjects":["Amusements -- Religious aspects"],"bookshelves":[],"languages":["en"],"copyright":false,"media_type":"Text","formats":{"text/html":"https://www.gutenberg.org/ebooks/45677.html.images","text/html; charset=iso-8859-1":"https://www.gutenberg.org/files/45677/45677-h/45677-h.htm","application/epub+zip":"https://www.gutenberg.org/ebooks/45677.epub3.images","application/x-mobipocket-ebook":"https://www.gutenberg.org/ebooks/45677.kf8.images","text/plain; charset=us-ascii":"https://www.gutenberg.org/ebooks/45677.txt.utf-8","text/plain; charset=iso-8859-1":"https://www.gutenberg.org/files/45677/45677-8.txt","application/rdf+xml":"https://www.gutenberg.org/ebooks/45677.rdf","image/jpeg":"https://www.gutenberg.org/cache/epub/45677/pg45677.cover.medium.jpg","application/octet-stream":"https://www.gutenberg.org/cache/epub/45677/pg45677-h.zip"},"download_count":65},{"id":45706,"title":"The Overland Guide-book: A complete vade-mecum for the overland traveller, to India viâ Egypt.","authors":[{"name":"Barber, James, active 1837-1839","birth_year":null,"death_year":null}],"translators":[],"subjects":["Travel -- Guidebooks"],"bookshelves":[],"languages":["en"],"copyright":false,"media_type":"Text","formats":{"text/html":"https://www.gutenberg.org/ebooks/45706.html.images","text/html; charset=iso-8859-1":"https://www.gutenberg.org/files/45706/45706-h/45706-h.htm","application/epub+zip":"https://www.gutenberg.org/ebooks/45706.epub3.images","application/x-mobipocket-ebook":"https://www.gutenberg.org/ebooks/45706.kf8.images","text/plain; charset=us-ascii":"https://www.gutenberg.org/ebooks/45706.txt.utf-8","text/plain; charset=iso-8859-1":"https://www.gutenberg.org/files/45706/45706-8.txt","application/rdf+xml":"https://www.gutenberg.org/ebooks/45706.rdf","image/jpeg":"https://www.gutenberg.org/cache/epub/45706/pg45706.cover.medium.jpg","application/octet-stream":"https://www.gutenberg.org/cache/epub/45706/pg45706-h.zip"},"download_count":65},{"id":45729,"title":"Buffon's Natural History. Volume 04 (of 10): Containing a Theory of the Earth, a General History of Man, of the Brute Creation, and of Vegetables, Minerals, &c. &c","authors":[{"name":"Buffon, Georges Louis Leclerc, comte de","birth_year":1707,"death_year":1788}],"translators":[],"subjects":["Natural history"],"bookshelves":[],"languages":["en"],"copyright":false,"media_type":"Text","formats":{"text/html":"https://www.gutenberg.org/ebooks/45729.html.images","text/html; charset=iso-8859-1":"https://www.gutenberg.org/files/45729/45729-h/45729-h.htm","application/epub+zip":"https://www.gutenberg.org/ebooks/45729.epub3.images","application/x-mobipocket-ebook":"https://www.gutenberg.org/ebooks/45729.kf8.images","text/plain; charset=us-ascii":"https://www.gutenberg.org/ebooks/45729.txt.utf-8","text/plain; charset=iso-8859-1":"https://www.gutenberg.org/files/45729/45729-8.txt","application/rdf+xml":"https://www.gutenberg.org/ebooks/45729.rdf","image/jpeg":"https://www.gutenberg.org/cache/epub/45729/pg45729.cover.medium.jpg","application/octet-stream":"https://www.gutenberg.org/cache/epub/45729/pg45729-h.zip"},"download_count":65},{"id":45802,"title":"Knock Three Times!","authors":[{"name":"Webb, Marion St. John","birth_year":null,"death_year":1930}],"translators":[],"subjects":["Fantasy fiction","Siblings -- Juvenile fiction","Twins -- Juvenile fiction"],"bookshelves":[],"languages":["en"],"copyright":false,"media_type":"Text","formats":{"text/html":"https://www.gutenberg.org/ebooks/45802.html.images","text/html; charset=utf-8":"https://www.gutenberg.org/files/45802/45802-h/45802-h.htm","application/epub+zip":"https://www.gutenberg.org/ebooks/45802.epub3.images","application/x-mobipocket-ebook":"https://www.gutenberg.org/ebooks/45802.kf8.images","text/plain; charset=us-ascii":"https://www.gutenberg.org/ebooks/45802.txt.utf-8","text/plain; charset=utf-8":"https://www.gutenberg.org/files/45802/45802-0.txt","text/plain; charset=iso-8859-1":"https://www.gutenberg.org/files/45802/45802-8.txt","application/rdf+xml":"https://www.gutenberg.org/ebooks/45802.rdf","image/jpeg":"https://www.gutenberg.org/cache/epub/45802/pg45802.cover.medium.jpg","application/octet-stream":"https://www.gutenberg.org/cache/epub/45802/pg45802-h.zip"},"download_count":65},{"id":45844,"title":"Our Little Persian Cousin","authors":[{"name":"Shedd, E. Cutler (Ephraim Cutler)","birth_year":null,"death_year":null}],"translators":[],"subjects":["Children -- Iran -- Juvenile literature"],"bookshelves":[],"languages":["en"],"copyright":false,"media_type":"Text","formats":{"text/html":"https://www.gutenberg.org/ebooks/45844.html.images","text/html; charset=iso-8859-1":"https://www.gutenberg.org/files/45844/45844-h/45844-h.htm","application/epub+zip":"https://www.gutenberg.org/ebooks/45844.epub3.images","application/x-mobipocket-ebook":"https://www.gutenberg.org/ebooks/45844.kf8.images","text/plain; charset=us-ascii":"https://www.gutenberg.org/ebooks/45844.txt.utf-8","text/plain; charset=iso-8859-1":"https://www.gutenberg.org/files/45844/45844-8.txt","application/rdf+xml":"https://www.gutenberg.org/ebooks/45844.rdf","image/jpeg":"https://www.gutenberg.org/cache/epub/45844/pg45844.cover.medium.jpg","application/octet-stream":"https://www.gutenberg.org/cache/epub/45844/pg45844-h.zip"},"download_count":65},{"id":46122,"title":"The Story of the Pullman Car","authors":[{"name":"Husband, Joseph","birth_year":1885,"death_year":1938}],"translators":[],"subjects":["Pullman Company","Pullman cars"],"bookshelves":[],"languages":["en"],"copyright":false,"media_type":"Text","formats":{"text/html":"https://www.gutenberg.org/ebooks/46122.html.images","text/html; charset=iso-8859-1":"https://www.gutenberg.org/files/46122/46122-h/46122-h.htm","application/epub+zip":"https://www.gutenberg.org/ebooks/46122.epub3.images","application/x-mobipocket-ebook":"https://www.gutenberg.org/ebooks/46122.kf8.images","text/plain; charset=us-ascii":"https://www.gutenberg.org/ebooks/46122.txt.utf-8","text/plain; charset=iso-8859-1":"https://www.gutenberg.org/files/46122/46122-8.txt","application/rdf+xml":"https://www.gutenberg.org/ebooks/46122.rdf","image/jpeg":"https://www.gutenberg.org/cache/epub/46122/pg46122.cover.medium.jpg","application/octet-stream":"https://www.gutenberg.org/cache/epub/46122/pg46122-h.zip"},"download_count":65},{"id":46125,"title":"Pablo de Segovia, the Spanish Sharper","authors":[{"name":"Quevedo, Francisco de","birth_year":1580,"death_year":1645}],"translators":[],"subjects":["Picaresque literature, Spanish","Spain -- Fiction","Swindlers and swindling -- Fiction"],"bookshelves":[],"languages":["en"],"copyright":false,"media_type":"Text","formats":{"text/html":"https://www.gutenberg.org/ebooks/46125.html.images","text/html; charset=utf-8":"https://www.gutenberg.org/files/46125/46125-h/46125-h.htm","application/epub+zip":"https://www.gutenberg.org/ebooks/46125.epub3.images","application/x-mobipocket-ebook":"https://www.gutenberg.org/ebooks/46125.kf8.images","text/plain; charset=us-ascii":"https://www.gutenberg.org/ebooks/46125.txt.utf-8","text/plain; charset=iso-8859-1":"https://www.gutenberg.org/files/46125/46125-8.txt","application/rdf+xml":"https://www.gutenberg.org/ebooks/46125.rdf","image/jpeg":"https://www.gutenberg.org/cache/epub/46125/pg46125.cover.medium.jpg","application/octet-stream":"https://www.gutenberg.org/cache/epub/46125/pg46125-h.zip"},"download_count":65},{"id":46190,"title":"Stories of Robin Hood","authors":[{"name":"Bush, Bertha Evangeline","birth_year":1866,"death_year":null}],"translators":[],"subjects":["Robin Hood (Legendary character) -- Juvenile literature"],"bookshelves":[],"languages":["en"],"copyright":false,"media_type":"Text","formats":{"text/html":"https://www.gutenberg.org/ebooks/46190.html.images","text/html; charset=iso-8859-1":"https://www.gutenberg.org/files/46190/46190-h/46190-h.htm","application/epub+zip":"https://www.gutenberg.org/ebooks/46190.epub3.images","application/x-mobipocket-ebook":"https://www.gutenberg.org/ebooks/46190.kf8.images","text/plain; charset=us-ascii":"https://www.gutenberg.org/ebooks/46190.txt.utf-8","text/plain; charset=iso-8859-1":"https://www.gutenberg.org/files/46190/46190-8.txt","application/rdf+xml":"https://www.gutenberg.org/ebooks/46190.rdf","image/jpeg":"https://www.gutenberg.org/cache/epub/46190/pg46190.cover.medium.jpg","application/octet-stream":"https://www.gutenberg.org/cache/epub/46190/pg46190-h.zip"},"download_count":65},{"id":46827,"title":"The Book of Jade","authors":[{"name":"Barnitz, David Park","birth_year":1878,"death_year":1901}],"translators":[],"subjects":["American poetry"],"bookshelves":[],"languages":["en"],"copyright":false,"media_type":"Text","formats":{"text/html":"https://www.gutenberg.org/ebooks/46827.html.images","text/html; charset=iso-8859-1":"https://www.gutenberg.org/files/46827/46827-h/46827-h.htm","application/epub+zip":"https://www.gutenberg.org/ebooks/46827.epub3.images","application/x-mobipocket-ebook":"https://www.gutenberg.org/ebooks/46827.kf8.images","text/plain; charset=us-ascii":"https://www.gutenberg.org/ebooks/46827.txt.utf-8","text/plain; charset=iso-8859-1":"https://www.gutenberg.org/files/46827/46827-8.txt","application/rdf+xml":"https://www.gutenberg.org/ebooks/46827.rdf","image/jpeg":"https://www.gutenberg.org/cache/epub/46827/pg46827.cover.medium.jpg","application/octet-stream":"https://www.gutenberg.org/cache/epub/46827/pg46827-h.zip"},"download_count":65},{"id":47136,"title":"Schopenhauer","authors":[{"name":"Beer, Margrieta","birth_year":null,"death_year":null}],"translators":[],"subjects":["Schopenhauer, Arthur, 1788-1860"],"bookshelves":[],"languages":["en"],"copyright":false,"media_type":"Text","formats":{"text/html":"https://www.gutenberg.org/ebooks/47136.html.images","text/html; charset=iso-8859-1":"https://www.gutenberg.org/files/47136/47136-h/47136-h.htm","application/epub+zip":"https://www.gutenberg.org/ebooks/47136.epub3.images","application/x-mobipocket-ebook":"https://www.gutenberg.org/ebooks/47136.kf8.images","text/plain; charset=us-ascii":"https://www.gutenberg.org/ebooks/47136.txt.utf-8","text/plain; charset=iso-8859-1":"https://www.gutenberg.org/files/47136/47136-8.txt","application/rdf+xml":"https://www.gutenberg.org/ebooks/47136.rdf","image/jpeg":"https://www.gutenberg.org/cache/epub/47136/pg47136.cover.medium.jpg","application/octet-stream":"https://www.gutenberg.org/cache/epub/47136/pg47136-h.zip"},"download_count":65},{"id":47408,"title":"Folk-Lore and Legends: English","authors":[],"translators":[],"subjects":["Legends -- England","Tales -- England"],"bookshelves":[],"languages":["en"],"copyright":false,"media_type":"Text","formats":{"text/html":"https://www.gutenberg.org/ebooks/47408.html.images","text/html; charset=utf-8":"https://www.gutenberg.org/files/47408/47408-h/47408-h.htm","application/epub+zip":"https://www.gutenberg.org/ebooks/47408.epub3.images","application/x-mobipocket-ebook":"https://www.gutenberg.org/ebooks/47408.kf8.images","text/plain; charset=us-ascii":"https://www.gutenberg.org/ebooks/47408.txt.utf-8","text/plain; charset=utf-8":"https://www.gutenberg.org/files/47408/47408-0.txt","application/rdf+xml":"https://www.gutenberg.org/ebooks/47408.rdf","image/jpeg":"https://www.gutenberg.org/cache/epub/47408/pg47408.cover.medium.jpg","application/octet-stream":"https://www.gutenberg.org/cache/epub/47408/pg47408-h.zip"},"download_count":65},{"id":47427,"title":"The Dance of Death","authors":[{"name":"Herman, William (Author of The dance of death)","birth_year":null,"death_year":null}],"translators":[],"subjects":["Satire","Waltz -- Social aspects"],"bookshelves":[],"languages":["en"],"copyright":false,"media_type":"Text","formats":{"text/html":"https://www.gutenberg.org/ebooks/47427.html.images","text/html; charset=iso-8859-1":"https://www.gutenberg.org/files/47427/47427-h/47427-h.htm","application/epub+zip":"https://www.gutenberg.org/ebooks/47427.epub3.images","application/x-mobipocket-ebook":"https://www.gutenberg.org/ebooks/47427.kf8.images","text/plain; charset=us-ascii":"https://www.gutenberg.org/ebooks/47427.txt.utf-8","text/plain; charset=iso-8859-1":"https://www.gutenberg.org/files/47427/47427-8.txt","application/rdf+xml":"https://www.gutenberg.org/ebooks/47427.rdf","image/jpeg":"https://www.gutenberg.org/cache/epub/47427/pg47427.cover.medium.jpg","application/octet-stream":"https://www.gutenberg.org/cache/epub/47427/pg47427-h.zip"},"download_count":65},{"id":47800,"title":"Highways and Byways in the Border: Illustrated","authors":[{"name":"Lang, Andrew","birth_year":1844,"death_year":1912},{"name":"Lang, John","birth_year":1849,"death_year":1917}],"translators":[],"subjects":["Scottish Borders (Scotland) -- Description and travel"],"bookshelves":[],"languages":["en"],"copyright":false,"media_type":"Text","formats":{"text/html":"https://www.gutenberg.org/ebooks/47800.html.images","text/html; charset=iso-8859-1":"https://www.gutenberg.org/files/47800/47800-h/47800-h.htm","application/epub+zip":"https://www.gutenberg.org/ebooks/47800.epub3.images","application/x-mobipocket-ebook":"https://www.gutenberg.org/ebooks/47800.kf8.images","text/plain; charset=us-ascii":"https://www.gutenberg.org/ebooks/47800.txt.utf-8","text/plain; charset=iso-8859-1":"https://www.gutenberg.org/files/47800/47800-8.txt","application/rdf+xml":"https://www.gutenberg.org/ebooks/47800.rdf","image/jpeg":"https://www.gutenberg.org/cache/epub/47800/pg47800.cover.medium.jpg","application/octet-stream":"https://www.gutenberg.org/cache/epub/47800/pg47800-h.zip"},"download_count":65},{"id":47824,"title":"The Pier-Glass","authors":[{"name":"Graves, Robert","birth_year":1895,"death_year":1985}],"translators":[],"subjects":["English poetry -- 20th century"],"bookshelves":[],"languages":["en"],"copyright":false,"media_type":"Text","formats":{"text/html":"https://www.gutenberg.org/ebooks/47824.html.images","application/epub+zip":"https://www.gutenberg.org/ebooks/47824.epub3.images","application/x-mobipocket-ebook":"https://www.gutenberg.org/ebooks/47824.kf8.images","text/plain; charset=us-ascii":"https://www.gutenberg.org/ebooks/47824.txt.utf-8","text/plain; charset=iso-8859-1":"https://www.gutenberg.org/files/47824/47824-8.txt","application/rdf+xml":"https://www.gutenberg.org/ebooks/47824.rdf","image/jpeg":"https://www.gutenberg.org/cache/epub/47824/pg47824.cover.medium.jpg","application/octet-stream":"https://www.gutenberg.org/cache/epub/47824/pg47824-h.zip"},"download_count":65},{"id":47970,"title":"The Dwelling House","authors":[{"name":"Poore, George Vivian","birth_year":1843,"death_year":1904}],"translators":[],"subjects":["Plumbing","Sanitary engineering"],"bookshelves":[],"languages":["en"],"copyright":false,"media_type":"Text","formats":{"text/html":"https://www.gutenberg.org/ebooks/47970.html.images","text/html; charset=utf-8":"https://www.gutenberg.org/files/47970/47970-h/47970-h.htm","application/epub+zip":"https://www.gutenberg.org/ebooks/47970.epub3.images","application/x-mobipocket-ebook":"https://www.gutenberg.org/ebooks/47970.kf8.images","text/plain; charset=us-ascii":"https://www.gutenberg.org/ebooks/47970.txt.utf-8","text/plain; charset=utf-8":"https://www.gutenberg.org/files/47970/47970-0.txt","application/rdf+xml":"https://www.gutenberg.org/ebooks/47970.rdf","image/jpeg":"https://www.gutenberg.org/cache/epub/47970/pg47970.cover.medium.jpg","application/octet-stream":"https://www.gutenberg.org/cache/epub/47970/pg47970-h.zip"},"download_count":65},{"id":48507,"title":"Devonshire Characters and Strange Events","authors":[{"name":"Baring-Gould, S. (Sabine)","birth_year":1834,"death_year":1924}],"translators":[],"subjects":["Devon (England) -- Biography","Devon (England) -- History"],"bookshelves":[],"languages":["en"],"copyright":false,"media_type":"Text","formats":{"text/html":"https://www.gutenberg.org/ebooks/48507.html.images","text/html; charset=iso-8859-1":"https://www.gutenberg.org/files/48507/48507-h/48507-h.htm","application/epub+zip":"https://www.gutenberg.org/ebooks/48507.epub3.images","application/x-mobipocket-ebook":"https://www.gutenberg.org/ebooks/48507.kf8.images","text/plain; charset=us-ascii":"https://www.gutenberg.org/ebooks/48507.txt.utf-8","text/plain; charset=utf-8":"https://www.gutenberg.org/files/48507/48507-0.txt","application/rdf+xml":"https://www.gutenberg.org/ebooks/48507.rdf","image/jpeg":"https://www.gutenberg.org/cache/epub/48507/pg48507.cover.medium.jpg","application/octet-stream":"https://www.gutenberg.org/cache/epub/48507/pg48507-h.zip"},"download_count":65},{"id":49622,"title":"Handbook of Birmingham: Prepared for the Members of the British Association, 1886","authors":[{"name":"British Association for the Advancement of Science","birth_year":null,"death_year":null}],"translators":[],"subjects":["Birmingham (England)","Natural history -- England -- Birmingham"],"bookshelves":[],"languages":["en"],"copyright":false,"media_type":"Text","formats":{"text/html":"https://www.gutenberg.org/ebooks/49622.html.images","text/html; charset=utf-8":"https://www.gutenberg.org/files/49622/49622-h/49622-h.htm","application/epub+zip":"https://www.gutenberg.org/ebooks/49622.epub3.images","application/x-mobipocket-ebook":"https://www.gutenberg.org/ebooks/49622.kf8.images","text/plain; charset=us-ascii":"https://www.gutenberg.org/ebooks/49622.txt.utf-8","text/plain; charset=utf-8":"https://www.gutenberg.org/files/49622/49622-0.txt","application/rdf+xml":"https://www.gutenberg.org/ebooks/49622.rdf","image/jpeg":"https://www.gutenberg.org/cache/epub/49622/pg49622.cover.medium.jpg","application/octet-stream":"https://www.gutenberg.org/cache/epub/49622/pg49622-h.zip"},"download_count":65},{"id":49708,"title":"The Garden of Eden: Stories from the first nine books of the Old Testament","authors":[{"name":"Hodges, George","birth_year":1856,"death_year":1919}],"translators":[],"subjects":["Bible stories, English -- Old Testament"],"bookshelves":[],"languages":["en"],"copyright":false,"media_type":"Text","formats":{"text/html":"https://www.gutenberg.org/ebooks/49708.html.images","text/html; charset=utf-8":"https://www.gutenberg.org/files/49708/49708-h/49708-h.htm","application/epub+zip":"https://www.gutenberg.org/ebooks/49708.epub3.images","application/x-mobipocket-ebook":"https://www.gutenberg.org/ebooks/49708.kf8.images","text/plain; charset=us-ascii":"https://www.gutenberg.org/ebooks/49708.txt.utf-8","text/plain; charset=utf-8":"https://www.gutenberg.org/files/49708/49708-0.txt","application/rdf+xml":"https://www.gutenberg.org/ebooks/49708.rdf","image/jpeg":"https://www.gutenberg.org/cache/epub/49708/pg49708.cover.medium.jpg","application/octet-stream":"https://www.gutenberg.org/cache/epub/49708/pg49708-h.zip"},"download_count":65},{"id":50361,"title":"Wet Magic","authors":[{"name":"Nesbit, E. (Edith)","birth_year":1858,"death_year":1924}],"translators":[],"subjects":["Circus -- Juvenile fiction","Fantasy fiction","Mermaids -- Juvenile fiction","War -- Juvenile fiction"],"bookshelves":[],"languages":["en"],"copyright":false,"media_type":"Text","formats":{"text/html":"https://www.gutenberg.org/ebooks/50361.html.images","application/epub+zip":"https://www.gutenberg.org/ebooks/50361.epub3.images","application/x-mobipocket-ebook":"https://www.gutenberg.org/ebooks/50361.kf8.images","text/plain; charset=us-ascii":"https://www.gutenberg.org/ebooks/50361.txt.utf-8","application/rdf+xml":"https://www.gutenberg.org/ebooks/50361.rdf","image/jpeg":"https://www.gutenberg.org/cache/epub/50361/pg50361.cover.medium.jpg","application/octet-stream":"https://www.gutenberg.org/files/50361/50361-0.zip"},"download_count":65},{"id":50505,"title":"Dick Kent in the Far North","authors":[{"name":"Oblinger, M. M. (Milo Milton)","birth_year":1900,"death_year":null}],"translators":[],"subjects":["Adventure stories","Canada, Northern -- Juvenile fiction","Royal Canadian Mounted Police -- Juvenile fiction"],"bookshelves":[],"languages":["en"],"copyright":false,"media_type":"Text","formats":{"text/html":"https://www.gutenberg.org/ebooks/50505.html.images","text/html; charset=utf-8":"https://www.gutenberg.org/files/50505/50505-h/50505-h.htm","application/epub+zip":"https://www.gutenberg.org/ebooks/50505.epub3.images","application/x-mobipocket-ebook":"https://www.gutenberg.org/ebooks/50505.kf8.images","text/plain; charset=us-ascii":"https://www.gutenberg.org/ebooks/50505.txt.utf-8","text/plain; charset=utf-8":"https://www.gutenberg.org/files/50505/50505-0.txt","application/rdf+xml":"https://www.gutenberg.org/ebooks/50505.rdf","image/jpeg":"https://www.gutenberg.org/cache/epub/50505/pg50505.cover.medium.jpg","application/octet-stream":"https://www.gutenberg.org/cache/epub/50505/pg50505-h.zip"},"download_count":65},{"id":51295,"title":"The Man Who Was Six","authors":[{"name":"Wallace, F. L. (Floyd L.)","birth_year":1915,"death_year":2004}],"translators":[],"subjects":["Accident victims -- Fiction","Amnesiacs -- Fiction","Identity -- Fiction","Science fiction","Spouses -- Fiction"],"bookshelves":["Science Fiction"],"languages":["en"],"copyright":false,"media_type":"Text","formats":{"text/html":"https://www.gutenberg.org/ebooks/51295.html.images","text/html; charset=us-ascii":"https://www.gutenberg.org/files/51295/51295-h/51295-h.htm","application/epub+zip":"https://www.gutenberg.org/ebooks/51295.epub3.images","application/x-mobipocket-ebook":"https://www.gutenberg.org/ebooks/51295.kf8.images","text/plain; charset=us-ascii":"https://www.gutenberg.org/ebooks/51295.txt.utf-8","application/rdf+xml":"https://www.gutenberg.org/ebooks/51295.rdf","image/jpeg":"https://www.gutenberg.org/cache/epub/51295/pg51295.cover.medium.jpg","application/octet-stream":"https://www.gutenberg.org/cache/epub/51295/pg51295-h.zip"},"download_count":65},{"id":51546,"title":"Handyman","authors":[{"name":"Banta, Frank","birth_year":null,"death_year":null}],"translators":[],"subjects":["Prisoners -- Fiction","Science fiction","Short stories"],"bookshelves":["Science Fiction"],"languages":["en"],"copyright":false,"media_type":"Text","formats":{"text/html":"https://www.gutenberg.org/ebooks/51546.html.images","text/html; charset=us-ascii":"https://www.gutenberg.org/files/51546/51546-h/51546-h.htm","application/epub+zip":"https://www.gutenberg.org/ebooks/51546.epub3.images","application/x-mobipocket-ebook":"https://www.gutenberg.org/ebooks/51546.kf8.images","text/plain; charset=us-ascii":"https://www.gutenberg.org/ebooks/51546.txt.utf-8","application/rdf+xml":"https://www.gutenberg.org/ebooks/51546.rdf","image/jpeg":"https://www.gutenberg.org/cache/epub/51546/pg51546.cover.medium.jpg","application/octet-stream":"https://www.gutenberg.org/cache/epub/51546/pg51546-h.zip"},"download_count":65},{"id":51547,"title":"The Story of the Airship (Non-rigid): A Study of One of America's Lesser Known Defense Weapons","authors":[{"name":"Allen, Hugh","birth_year":1882,"death_year":1977}],"translators":[],"subjects":["Military airships -- United States"],"bookshelves":["World War II"],"languages":["en"],"copyright":false,"media_type":"Text","formats":{"text/html":"https://www.gutenberg.org/ebooks/51547.html.images","text/html; charset=utf-8":"https://www.gutenberg.org/files/51547/51547-h/51547-h.htm","application/epub+zip":"https://www.gutenberg.org/ebooks/51547.epub3.images","application/x-mobipocket-ebook":"https://www.gutenberg.org/ebooks/51547.kf8.images","text/plain; charset=us-ascii":"https://www.gutenberg.org/ebooks/51547.txt.utf-8","text/plain; charset=utf-8":"https://www.gutenberg.org/files/51547/51547-0.txt","text/plain; charset=iso-8859-1":"https://www.gutenberg.org/files/51547/51547-8.txt","application/rdf+xml":"https://www.gutenberg.org/ebooks/51547.rdf","image/jpeg":"https://www.gutenberg.org/cache/epub/51547/pg51547.cover.medium.jpg","application/octet-stream":"https://www.gutenberg.org/cache/epub/51547/pg51547-h.zip"},"download_count":65}]}