{"count":58808,"next":"http://129.241.150.113:8000/books/?languages=en&page=1086","previous":"http://129.241.150.113:8000/books/?languages=en&page=1084","results":[{"id":62084,"title":"The Deceased Wife's Sister, and My Beautiful Neighbour, v. 3","authors":[{"name":"Russell, William Clark","birth_year":1844,"death_year":1911}],"translators":[],"subjects":["English fiction -- 19th century"],"bookshelves":[],"languages":["en"],"copyright":false,"media_type":"Text","formats":{"text/html":"https://www.gutenberg.org/ebooks/62084.html.images","text/html; charset=iso-8859-1":"https://www.gutenberg.org/files/62084/62084-h/62084-h.htm","application/epub+zip":"https://www.gutenberg.org/ebooks/62084.epub3.images","application/x-mobipocket-ebook":"https://www.gutenberg.org/ebooks/62084.kf8.images","text/plain; charset=us-ascii":"https://www.gutenberg.org/ebooks/62084.txt.utf-8","text/plain; charset=iso-8859-1":"https://www.gutenberg.org/files/62084/62084-8.txt","application/rdf+xml":"https://www.gutenberg.org/ebooks/62084.rdf","image/jpeg":"https://www.gutenberg.org/cache/epub/62084/pg62084.cover.medium.jpg","application/octet-stream":"https://www.gutenberg.org/cache/epub/62084/pg62084-h.zip"},"download_count":34},{"id":62184,"title":"For God and Gold","authors":[{"name":"Corbett, Julian Stafford","birth_year":1854,"death_year":1922}],"translators":[],"subjects":["Drake, Francis, approximately 1540-1596 -- Fiction","Great Britain -- History -- Elizabeth, 1558-1603 -- Fiction","Historical fiction"],"bookshelves":[],"languages":["en"],"copyright":false,"media_type":"Text","formats":{"text/html":"https://www.gutenberg.org/ebooks/62184.html.images","text/html; charset=iso-8859-1":"https://www.gutenberg.org/files/62184/62184-h/62184-h.htm","application/epub+zip":"https://www.gutenberg.org/ebooks/62184.epub3.images","application/x-mobipocket-ebook":"https://www.gutenberg.org/ebooks/62184.kf8.images","text/plain; charset=us-ascii":"https://www.gutenberg.org/ebooks/62184.txt.utf-8","text/plain; charset=iso-8859-1":"https://www.gutenberg.org/files/62184/62184-8.txt","application/rdf+xml":"https://www.gutenberg.org/ebooks/62184.rdf","image/jpeg":"https://www.gutenberg.org/cache/epub/62184/pg62184.cover.medium.jpg","application/octet-stream":"https://www.gutenberg.org/cache/epub/62184/pg62184-h.zip"},"download_count":34},{"id":62229,"title":"The Story Without an End","authors":[{"name":"Carové, Friedrich Wilhelm","birth_year":1789,"death_year":1852}],"translators":[{"name":"Austin, Sarah","birth_year":1793,"death_year":1867}],"subjects":["Allegories","Animals -- Juvenile fiction","Children -- Conduct of life -- Juvenile fiction","Conduct of life -- Juvenile fiction","Natural history -- Juvenile fiction","Nature -- Juvenile fiction","Seasons -- Juvenile fiction"],"bookshelves":[],"languages":["en"],"copyright":false,"media_type":"Text","formats":{"text/html":"https://www.gutenberg.org/ebooks/62229.html.images","text/html; charset=iso-8859-1":"https://www.gutenberg.org/files/62229/62229-h/62229-h.htm","application/epub+zip":"https://www.gutenberg.org/ebooks/62229.epub3.images","application/x-mobipocket-ebook":"https://www.gutenberg.org/ebooks/62229.kf8.images","text/plain; charset=us-ascii":"https://www.gutenberg.org/ebooks/62229.txt.utf-8","text/plain; charset=utf-8":"https://www.gutenberg.org/files/62229/62229-0.txt","application/rdf+xml":"https://www.gutenberg.org/ebooks/62229.rdf","image/jpeg":"https://www.gutenberg.org/cache/epub/62229/pg62229.cover.medium.jpg","application/octet-stream":"https://www.gutenberg.org/cache/epub/62229/pg62229-h.zip"},"download_count":34},{"id":62279,"title":"Captain Billy's Whiz Bang, Vol. 3, No. 29, January, 1922: America's Magazine of Wit, Humor and Filosophy","authors":[{"name":"Various","birth_year":null,"death_year":null}],"translators":[],"subjects":["American wit and humor -- Periodicals"],"bookshelves":[],"languages":["en"],"copyright":false,"media_type":"Text","formats":{"text/html":"https://www.gutenberg.org/ebooks/62279.html.images","text/html; charset=utf-8":"https://www.gutenberg.org/files/62279/62279-h/62279-h.htm","application/epub+zip":"https://www.gutenberg.org/ebooks/62279.epub3.images","application/x-mobipocket-ebook":"https://www.gutenberg.org/ebooks/62279.kf8.images","text/plain; charset=us-ascii":"https://www.gutenberg.org/ebooks/62279.txt.utf-8","text/plain; charset=utf-8":"https://www.gutenberg.org/files/62279/62279-0.txt","application/rdf+xml":"https://www.gutenberg.org/ebooks/62279.rdf","image/jpeg":"https://www.gutenberg.org/cache/epub/62279/pg62279.cover.medium.jpg","application/octet-stream":"https://www.gutenberg.org/cache/epub/62279/pg62279-h.zip"},"download_count":34},{"id":62284,"title":"Apples in Appealing Ways [1969]","authors":[{"name":"United States. Agricultural Research Service. Human Nutrition Research Division","birth_year":null,"death_year":null}],"translators":[],"subjects":["Cooking (Apples)"],"bookshelves":[],"languages":["en"],"copyright":false,"media_type":"Text","formats":{"text/html":"https://www.gutenberg.org/ebooks/62284.html.images","text/html; charset=utf-8":"https://www.gutenberg.org/files/62284/62284-h/62284-h.htm","application/epub+zip":"https://www.gutenberg.org/ebooks/62284.epub3.images","application/x-mobipocket-ebook":"https://www.gutenberg.org/ebooks/62284.kf8.images","text/plain; charset=us-ascii":"https://www.gutenberg.org/ebooks/62284.txt.utf-8","text/plain; charset=utf-8":"https://www.gutenberg.org/files/62284/62284-0.txt","application/rdf+xml":"https://www.gutenberg.org/ebooks/62284.rdf","image/jpeg":"https://www.gutenberg.org/cache/epub/62284/pg62284.cover.medium.jpg","application/octet-stream":"https://www.gutenberg.org/cache/epub/62284/pg62284-h.zip"},"download_count":34},{"id":62287,"title":"The Collector's Guide, No. 17, January 1940: A monthly periodical devoted to first editions, Americana, autographs, old newspapers and magazines, sheet music, playbills, dime novels, current auction prices, etc.","authors":[{"name":"Various","birth_year":null,"death_year":null}],"translators":[],"subjects":["Book collecting -- Periodicals"],"bookshelves":[],"languages":["en"],"copyright":false,"media_type":"Text","formats":{"text/html":"https://www.gutenberg.org/ebooks/62287.html.images","text/html; charset=utf-8":"https://www.gutenberg.org/files/62287/62287-h/62287-h.htm","application/epub+zip":"https://www.gutenberg.org/ebooks/62287.epub3.images","application/x-mobipocket-ebook":"https://www.gutenberg.org/ebooks/62287.kf8.images","text/plain; charset=us-ascii":"https://www.gutenberg.org/ebooks/62287.txt.utf-8","text/plain; charset=utf-8":"https://www.gutenberg.org/files/62287/62287-0.txt","application/rdf+xml":"https://www.gutenberg.org/ebooks/62287.rdf","image/jpeg":"https://www.gutenberg.org/cache/epub/62287/pg62287.cover.medium.jpg","application/octet-stream":"https://www.gutenberg.org/cache/epub/62287/pg62287-h.zip"},"download_count":34},{"id":62336,"title":"Master Rockafellar's Voyage","authors":[{"name":"Russell, William Clark","birth_year":1844,"death_year":1911}],"translators":[],"subjects":["Adventure stories","Conduct of life -- Juvenile fiction","Sailors -- Juvenile fiction","Seafaring life -- Juvenile fiction","Voyages and travels -- Juvenile fiction","Youth -- Conduct of life -- Juvenile fiction"],"bookshelves":[],"languages":["en"],"copyright":false,"media_type":"Text","formats":{"text/html":"https://www.gutenberg.org/ebooks/62336.html.images","text/html; charset=utf-8":"https://www.gutenberg.org/files/62336/62336-h/62336-h.htm","application/epub+zip":"https://www.gutenberg.org/ebooks/62336.epub3.images","application/x-mobipocket-ebook":"https://www.gutenberg.org/ebooks/62336.kf8.images","text/plain; charset=us-ascii":"https://www.gutenberg.org/ebooks/62336.txt.utf-8","text/plain; charset=utf-8":"https://www.gutenberg.org/files/62336/62336-0.txt","application/rdf+xml":"https://www.gutenberg.org/ebooks/62336.rdf","image/jpeg":"https://www.gutenberg.org/cache/epub/62336/pg62336.cover.medium.jpg","application/octet-stream":"https://www.gutenberg.org/cache/epub/62336/pg62336-h.zip"},"download_count":34},{"id":62351,"title":"Revenge of the Vera","authors":[{"name":"Hasse, Henry","birth_year":1913,"death_year":1977}],"translators":[],"subjects":["Revenge -- Fiction","Science fiction","Short stories","Space pirates -- Fiction","Space ships -- Fiction"],"bookshelves":[],"languages":["en"],"copyright":false,"media_type":"Text","formats":{"text/html":"https://www.gutenberg.org/ebooks/62351.html.images","text/html; charset=us-ascii":"https://www.gutenberg.org/files/62351/62351-h/62351-h.htm","application/epub+zip":"https://www.gutenberg.org/ebooks/62351.epub3.images","application/x-mobipocket-ebook":"https://www.gutenberg.org/ebooks/62351.kf8.images","text/plain; charset=us-ascii":"https://www.gutenberg.org/ebooks/62351.txt.utf-8","application/rdf+xml":"https://www.gutenberg.org/ebooks/62351.rdf","image/jpeg":"https://www.gutenberg.org/cache/epub/62351/pg62351.cover.medium.jpg","application/octet-stream":"https://www.gutenberg.org/cache/epub/62351/pg62351-h.zip"},"download_count":34},{"id":62418,"title":"The Amazing Years","authors":[{"name":"Ridge, W. Pett (William Pett)","birth_year":1859,"death_year":1930}],"translators":[],"subjects":["England -- Social life and customs -- 20th century -- Fiction","Families -- Fiction","Housekeepers -- Fiction","Social classes -- Fiction","World War, 1914-1918 -- England -- Fiction"],"bookshelves":[],"languages":["en"],"copyright":false,"media_type":"Text","formats":{"text/html":"https://www.gutenberg.org/ebooks/62418.html.images","application/epub+zip":"https://www.gutenberg.org/ebooks/62418.epub3.images","application/x-mobipocket-ebook":"https://www.gutenberg.org/ebooks/62418.kf8.images","text/plain; charset=us-ascii":"https://www.gutenberg.org/ebooks/62418.txt.utf-8","text/plain; charset=iso-8859-1":"https://www.gutenberg.org/files/62418/62418-8.txt","application/rdf+xml":"https://www.gutenberg.org/ebooks/62418.rdf","image/jpeg":"https://www.gutenberg.org/cache/epub/62418/pg62418.cover.medium.jpg","application/octet-stream":"https://www.gutenberg.org/cache/epub/62418/pg62418-h.zip"},"download_count":34},{"id":62469,"title":"The Sundered Streams: The History of a Memory That Had No Full Stops","authors":[{"name":"Farrer, Reginald","birth_year":1880,"death_year":1920}],"translators":[],"subjects":["Man-woman relationships -- Fiction","Reincarnation -- Fiction","Triangles (Interpersonal relations) -- Fiction"],"bookshelves":[],"languages":["en"],"copyright":false,"media_type":"Text","formats":{"text/html":"https://www.gutenberg.org/ebooks/62469.html.images","text/html; charset=utf-8":"https://www.gutenberg.org/files/62469/62469-h/62469-h.htm","application/epub+zip":"https://www.gutenberg.org/ebooks/62469.epub3.images","application/x-mobipocket-ebook":"https://www.gutenberg.org/ebooks/62469.kf8.images","text/plain; charset=us-ascii":"https://www.gutenberg.org/ebooks/62469.txt.utf-8","text/plain; charset=utf-8":"https://www.gutenberg.org/files/62469/62469-0.txt","application/rdf+xml":"https://www.gutenberg.org/ebooks/62469.rdf","image/jpeg":"https://www.gutenberg.org/cache/epub/62469/pg62469.cover.medium.jpg","application/octet-stream":"https://www.gutenberg.org/cache/epub/62469/pg62469-h.zip"},"download_count":34},{"id":62478,"title":"Proud Lady","authors":[{"name":"Boyce, Neith","birth_year":1872,"death_year":1951}],"translators":[],"subjects":["Husband and wife -- Fiction","Man-woman relationships -- Fiction","Middle West -- Fiction","Triangles (Interpersonal relations) -- Fiction","United States -- Social life and customs -- 19th century -- Fiction"],"bookshelves":[],"languages":["en"],"copyright":false,"media_type":"Text","formats":{"text/html":"https://www.gutenberg.org/ebooks/62478.html.images","text/html; charset=iso-8859-1":"https://www.gutenberg.org/files/62478/62478-h/62478-h.htm","application/epub+zip":"https://www.gutenberg.org/ebooks/62478.epub3.images","application/x-mobipocket-ebook":"https://www.gutenberg.org/ebooks/62478.kf8.images","text/plain; charset=us-ascii":"https://www.gutenberg.org/ebooks/62478.txt.utf-8","text/plain; charset=iso-8859-1":"https://www.gutenberg.org/files/62478/62478-8.txt","application/rdf+xml":"https://www.gutenberg.org/ebooks/62478.rdf","image/jpeg":"https://www.gutenberg.org/cache/epub/62478/pg62478.cover.medium.jpg","application/octet-stream":"https://www.gutenberg.org/cache/epub/62478/pg62478-h.zip"},"download_count":34},{"id":62490,"title":"Introduction to Our Bird Friends, Volume 2","authors":[{"name":"Carson, Lenwood Ballard","birth_year":null,"death_year":null}],"translators":[],"subjects":["Birds -- Kansas"],"bookshelves":[],"languages":["en"],"copyright":false,"media_type":"Text","formats":{"text/html":"https://www.gutenberg.org/ebooks/62490.html.images","text/html; charset=utf-8":"https://www.gutenberg.org/files/62490/62490-h/62490-h.htm","application/epub+zip":"https://www.gutenberg.org/ebooks/62490.epub3.images","application/x-mobipocket-ebook":"https://www.gutenberg.org/ebooks/62490.kf8.images","text/plain; charset=us-ascii":"https://www.gutenberg.org/ebooks/62490.txt.utf-8","text/plain; charset=utf-8":"https://www.gutenberg.org/files/62490/62490-0.txt","application/rdf+xml":"https://www.gutenberg.org/ebooks/62490.rdf","image/jpeg":"https://www.gutenberg.org/cache/epub/62490/pg62490.cover.medium.jpg","application/octet-stream":"https://www.gutenberg.org/cache/epub/62490/pg62490-h.zip"},"download_count":34},{"id":62573,"title":"The Edge of the Desert","authors":[{"name":"Dunbar, Ianthe M.","birth_year":null,"death_year":null}],"translators":[],"subjects":["Tunisia -- Description and travel","Tunisia -- Social life and customs"],"bookshelves":[],"languages":["en"],"copyright":false,"media_type":"Text","formats":{"text/html":"https://www.gutenberg.org/ebooks/62573.html.images","text/html; charset=utf-8":"https://www.gutenberg.org/files/62573/62573-h/62573-h.htm","application/epub+zip":"https://www.gutenberg.org/ebooks/62573.epub3.images","application/x-mobipocket-ebook":"https://www.gutenberg.org/ebooks/62573.kf8.images","text/plain; charset=us-ascii":"https://www.gutenberg.org/ebooks/62573.txt.utf-8","text/plain; charset=utf-8":"https://www.gutenberg.org/files/62573/62573-0.txt","application/rdf+xml":"https://www.gutenberg.org/ebooks/62573.rdf","image/jpeg":"https://www.gutenberg.org/cache/epub/62573/pg62573.cover.medium.jpg","application/octet-stream":"https://www.gutenberg.org/cache/epub/62573/pg62573-h.zip"},"download_count":34},{"id":62590,"title":"Guarding His Goal","authors":[{"name":"Barbour, Ralph Henry","birth_year":1870,"death_year":1944}],"translators":[],"subjects":["Boarding schools -- Juvenile fiction","Hockey -- Juvenile fiction","Teenage boys -- Juvenile fiction"],"bookshelves":[],"languages":["en"],"copyright":false,"media_type":"Text","formats":{"text/html":"https://www.gutenberg.org/ebooks/62590.html.images","text/html; charset=utf-8":"https://www.gutenberg.org/files/62590/62590-h/62590-h.htm","application/epub+zip":"https://www.gutenberg.org/ebooks/62590.epub3.images","application/x-mobipocket-ebook":"https://www.gutenberg.org/ebooks/62590.kf8.images","text/plain; charset=us-ascii":"https://www.gutenberg.org/ebooks/62590.txt.utf-8","text/plain; charset=utf-8":"https://www.gutenberg.org/files/62590/62590-0.txt","application/rdf+xml":"https://www.gutenberg.org/ebooks/62590.rdf","image/jpeg":"https://www.gutenberg.org/cache/epub/62590/pg62590.cover.medium.jpg","application/octet-stream":"https://www.gutenberg.org/cache/epub/62590/pg62590-h.zip"},"download_count":34},{"id":62597,"title":"Design of a Steel Railroad Warehouse","authors":[{"name":"Tallyn, Louis Liston","birth_year":null,"death_year":null}],"translators":[],"subjects":["Railroads -- Buildings and structures -- Design and construction"],"bookshelves":[],"languages":["en"],"copyright":false,"media_type":"Text","formats":{"text/html":"https://www.gutenberg.org/ebooks/62597.html.images","text/html; charset=utf-8":"https://www.gutenberg.org/files/62597/62597-h/62597-h.htm","application/epub+zip":"https://www.gutenberg.org/ebooks/62597.epub3.images","application/x-mobipocket-ebook":"https://www.gutenberg.org/ebooks/62597.kf8.images","text/plain; charset=us-ascii":"https://www.gutenberg.org/ebooks/62597.txt.utf-8","text/plain; charset=utf-8":"https://www.gutenberg.org/files/62597/62597-0.txt","application/rdf+xml":"https://www.gutenberg.org/ebooks/62597.rdf","image/jpeg":"https://www.gutenberg.org/cache/epub/62597/pg62597.cover.medium.jpg","application/octet-stream":"https://www.gutenberg.org/cache/epub/62597/pg62597-h.zip"},"download_count":34},{"id":62653,"title":"The Ball of Fire","authors":[{"name":"Chester, George Randolph","birth_year":1869,"death_year":1924},{"name":"Chester, Lillian","birth_year":1887,"death_year":1961}],"translators":[],"subjects":["Businessmen -- Fiction","Churches -- Fiction","Clergy -- Fiction","Man-woman relationships -- Fiction","New York (N.Y.) -- Fiction","Young women -- Fiction"],"bookshelves":[],"languages":["en"],"copyright":false,"media_type":"Text","formats":{"text/html":"https://www.gutenberg.org/ebooks/62653.html.images","text/html; charset=utf-8":"https://www.gutenberg.org/files/62653/62653-h/62653-h.htm","application/epub+zip":"https://www.gutenberg.org/ebooks/62653.epub3.images","application/x-mobipocket-ebook":"https://www.gutenberg.org/ebooks/62653.kf8.images","text/plain; charset=us-ascii":"https://www.gutenberg.org/ebooks/62653.txt.utf-8","text/plain; charset=utf-8":"https://www.gutenberg.org/files/62653/62653-0.txt","application/rdf+xml":"https://www.gutenberg.org/ebooks/62653.rdf","image/jpeg":"https://www.gutenberg.org/cache/epub/62653/pg62653.cover.medium.jpg","application/octet-stream":"https://www.gutenberg.org/cache/epub/62653/pg62653-h.zip"},"download_count":34},{"id":62720,"title":"A Short Narrative of an Extraordinary Delivery of Rabbets, Perform'd by Mr. John Howard Surgeon at Guilford","authors":[{"name":"St. André, Nathanael","birth_year":1680,"death_year":1776}],"translators":[],"subjects":["Factitious disorders","Fraud","Obstetrics -- Early works to 1800","Toft, Mary, 1703-1763"],"bookshelves":[],"languages":["en"],"copyright":false,"media_type":"Text","formats":{"text/html":"https://www.gutenberg.org/ebooks/62720.html.images","text/html; charset=utf-8":"https://www.gutenberg.org/files/62720/62720-h/62720-h.htm","application/epub+zip":"https://www.gutenberg.org/ebooks/62720.epub3.images","application/x-mobipocket-ebook":"https://www.gutenberg.org/ebooks/62720.kf8.images","text/plain; charset=us-ascii":"https://www.gutenberg.org/ebooks/62720.txt.utf-8","text/plain; charset=utf-8":"https://www.gutenberg.org/files/62720/62720-0.txt","application/rdf+xml":"https://www.gutenberg.org/ebooks/62720.rdf","image/jpeg":"https://www.gutenberg.org/cache/epub/62720/pg62720.cover.medium.jpg","application/octet-stream":"https://www.gutenberg.org/cache/epub/62720/pg62720-h.zip"},"download_count":34},{"id":62818,"title":"Armor and Arms: An elementary handbook and guide to the collection in the City Art Museum of St. Louis, Missouri, U.S.A.","authors":[{"name":"Hoopes, Thomas T.","birth_year":1898,"death_year":1981}],"translators":[],"subjects":["Armor -- Catalogs","Weapons -- Catalogs"],"bookshelves":[],"languages":["en"],"copyright":false,"media_type":"Text","formats":{"text/html":"https://www.gutenberg.org/ebooks/62818.html.images","text/html; charset=utf-8":"https://www.gutenberg.org/files/62818/62818-h/62818-h.htm","application/epub+zip":"https://www.gutenberg.org/ebooks/62818.epub3.images","application/x-mobipocket-ebook":"https://www.gutenberg.org/ebooks/62818.kf8.images","text/plain; charset=us-ascii":"https://www.gutenberg.org/ebooks/62818.txt.utf-8","text/plain; charset=utf-8":"https://www.gutenberg.org/files/62818/62818-0.txt","application/rdf+xml":"https://www.gutenberg.org/ebooks/62818.rdf","image/jpeg":"https://www.gutenberg.org/cache/epub/62818/pg62818.cover.medium.jpg","application/octet-stream":"https://www.gutenberg.org/cache/epub/62818/pg62818-h.zip"},"download_count":34},{"id":62832,"title":"Outdoor Cooking with Reynolds Wrap: How to prepare tastier campfire meals without pots, pans and dishes","authors":[{"name":"Reynolds Metals Company","birth_year":null,"death_year":null}],"translators":[],"subjects":["Aluminum foil","Outdoor cooking"],"bookshelves":[],"languages":["en"],"copyright":false,"media_type":"Text","formats":{"text/html":"https://www.gutenberg.org/ebooks/62832.html.images","text/html; charset=utf-8":"https://www.gutenberg.org/files/62832/62832-h/62832-h.htm","application/epub+zip":"https://www.gutenberg.org/ebooks/62832.epub3.images","application/x-mobipocket-ebook":"https://www.gutenberg.org/ebooks/62832.kf8.images","text/plain; charset=us-ascii":"https://www.gutenberg.org/ebooks/62832.txt.utf-8","text/plain; charset=utf-8":"https://www.gutenberg.org/files/62832/62832-0.txt","application/rdf+xml":"https://www.gutenberg.org/ebooks/62832.rdf","image/jpeg":"https://www.gutenberg.org/cache/epub/62832/pg62832.cover.medium.jpg","application/octet-stream":"https://www.gutenberg.org/cache/epub/62832/pg62832-h.zip"},"download_count":34},{"id":62875,"title":"The Queen Versus Billy, and Other Stories","authors":[{"name":"Osbourne, Lloyd","birth_year":1868,"death_year":1947}],"translators":[],"subjects":["Oceania -- Fiction","Short stories, American"],"bookshelves":[],"languages":["en"],"copyright":false,"media_type":"Text","formats":{"text/html":"https://www.gutenberg.org/ebooks/62875.html.images","application/epub+zip":"https://www.gutenberg.org/ebooks/62875.epub3.images","application/x-mobipocket-ebook":"https://www.gutenberg.org/ebooks/62875.kf8.images","text/plain; charset=us-ascii":"https://www.gutenberg.org/ebooks/62875.txt.utf-8","text/plain; charset=utf-8":"https://www.gutenberg.org/files/62875/62875-0.txt","application/rdf+xml":"https://www.gutenberg.org/ebooks/62875.rdf","image/jpeg":"https://www.gutenberg.org/cache/epub/62875/pg62875.cover.medium.jpg","application/octet-stream":"https://www.gutenberg.org/cache/epub/62875/pg62875-h.zip"},"download_count":34},{"id":62939,"title":"Essays Irish and American","authors":[{"name":"Yeats, John Butler","birth_year":1839,"death_year":1922}],"translators":[],"subjects":["Butler, Samuel, 1835-1902","Essays","Synge, J. M. (John Millington), 1871-1909","Watts, George Frederick, 1817-1904","Yeats, John Butler, 1839-1922"],"bookshelves":[],"languages":["en"],"copyright":false,"media_type":"Text","formats":{"text/html":"https://www.gutenberg.org/ebooks/62939.html.images","text/html; charset=utf-8":"https://www.gutenberg.org/files/62939/62939-h/62939-h.htm","application/epub+zip":"https://www.gutenberg.org/ebooks/62939.epub3.images","application/x-mobipocket-ebook":"https://www.gutenberg.org/ebooks/62939.kf8.images","text/plain; charset=us-ascii":"https://www.gutenberg.org/ebooks/62939.txt.utf-8","text/plain; charset=utf-8":"https://www.gutenberg.org/files/62939/62939-0.txt","application/rdf+xml":"https://www.gutenberg.org/ebooks/62939.rdf","image/jpeg":"https://www.gutenberg.org/cache/epub/62939/pg62939.cover.medium.jpg","application/octet-stream":"https://www.gutenberg.org/cache/epub/62939/pg62939-h.zip"},"download_count":34},{"id":63006,"title":"By-ways on Service: Notes from an Australian Journal","authors":[{"name":"Dinning, Hector","birth_year":1887,"death_year":null}],"translators":[],"subjects":["World War, 1914-1918 -- Personal narratives, Australian"],"bookshelves":[],"languages":["en"],"copyright":false,"media_type":"Text","formats":{"text/html":"https://www.gutenberg.org/ebooks/63006.html.images","text/html; charset=utf-8":"https://www.gutenberg.org/files/63006/63006-h/63006-h.htm","application/epub+zip":"https://www.gutenberg.org/ebooks/63006.epub3.images","application/x-mobipocket-ebook":"https://www.gutenberg.org/ebooks/63006.kf8.images","text/plain; charset=us-ascii":"https://www.gutenberg.org/ebooks/63006.txt.utf-8","text/plain; charset=utf-8":"https://www.gutenberg.org/files/63006/63006-0.txt","application/rdf+xml":"https://www.gutenberg.org/ebooks/63006.rdf","image/jpeg":"https://www.gutenberg.org/cache/epub/63006/pg63006.cover.medium.jpg","application/octet-stream":"https://www.gutenberg.org/cache/epub/63006/pg63006-h.zip"},"download_count":34},{"id":63093,"title":"Story of the Life of St. Paul, the Apostle","authors":[{"name":"Seymour, Mary, active 1880-1896","birth_year":null,"death_year":null}],"translators":[],"subjects":["Paul, the Apostle, Saint"],"bookshelves":[],"languages":["en"],"copyright":false,"media_type":"Text","formats":{"text/html":"https://www.gutenberg.org/ebooks/63093.html.images","text/html; charset=utf-8":"https://www.gutenberg.org/files/63093/63093-h/63093-h.htm","application/epub+zip":"https://www.gutenberg.org/ebooks/63093.epub3.images","application/x-mobipocket-ebook":"https://www.gutenberg.org/ebooks/63093.kf8.images","text/plain; charset=us-ascii":"https://www.gutenberg.org/ebooks/63093.txt.utf-8","text/plain; charset=utf-8":"https://www.gutenberg.org/files/63093/63093-0.txt","application/rdf+xml":"https://www.gutenberg.org/ebooks/63093.rdf","image/jpeg":"https://www.gutenberg.org/cache/epub/63093/pg63093.cover.medium.jpg","application/octet-stream":"https://www.gutenberg.org/cache/epub/63093/pg63093-h.zip"},"download_count":34},{"id":63163,"title":"Studies in the Wagnerian Drama","authors":[{"name":"Krehbiel, Henry Edward","birth_year":1854,"death_year":1923}],"translators":[],"subjects":["Wagner, Richard, 1813-1883. Operas"],"bookshelves":[],"languages":["en"],"copyright":false,"media_type":"Text","formats":{"text/html":"https://www.gutenberg.org/ebooks/63163.html.images","text/html; charset=iso-8859-1":"https://www.gutenberg.org/files/63163/63163-h/63163-h.htm","application/epub+zip":"https://www.gutenberg.org/ebooks/63163.epub3.images","application/x-mobipocket-ebook":"https://www.gutenberg.org/ebooks/63163.kf8.images","text/plain; charset=us-ascii":"https://www.gutenberg.org/ebooks/63163.txt.utf-8","text/plain; charset=utf-8":"https://www.gutenberg.org/files/63163/63163-0.txt","application/rdf+xml":"https://www.gutenberg.org/ebooks/63163.rdf","image/jpeg":"https://www.gutenberg.org/cache/epub/63163/pg63163.cover.medium.jpg","application/octet-stream":"https://www.gutenberg.org/cache/epub/63163/pg63163-h.zip"},"download_count":34},{"id":63173,"title":"The Son of Columbus","authors":[{"name":"Seawell, Molly Elliot","birth_year":1860,"death_year":1916}],"translators":[],"subjects":["Columbus, Christopher -- Fiction"],"bookshelves":[],"languages":["en"],"copyright":false,"media_type":"Text","formats":{"text/html":"https://www.gutenberg.org/ebooks/63173.html.images","text/html; charset=iso-8859-1":"https://www.gutenberg.org/files/63173/63173-h/63173-h.htm","application/epub+zip":"https://www.gutenberg.org/ebooks/63173.epub3.images","application/x-mobipocket-ebook":"https://www.gutenberg.org/ebooks/63173.kf8.images","text/plain; charset=us-ascii":"https://www.gutenberg.org/ebooks/63173.txt.utf-8","text/plain; charset=iso-8859-1":"https://www.gutenberg.org/files/63173/63173-8.txt","application/rdf+xml":"https://www.gutenberg.org/ebooks/63173.rdf","image/jpeg":"https://www.gutenberg.org/cache/epub/63173/pg63173.cover.medium.jpg","application/octet-stream":"https://www.gutenberg.org/cache/epub/63173/pg63173-h.zip"},"download_count":34},{"id":63297,"title":"The Brother of a Hero","authors":[{"name":"Barbour, Ralph Henry","birth_year":1870,"death_year":1944}],"translators":[],"subjects":["Boarding schools -- Juvenile fiction","Football -- Juvenile fiction","New York (State) -- Juvenile fiction","Teenage boys -- Juvenile fiction"],"bookshelves":[],"languages":["en"],"copyright":false,"media_type":"Text","formats":{"text/html":"https://www.gutenberg.org/ebooks/63297.html.images","text/html; charset=utf-8":"https://www.gutenberg.org/files/63297/63297-h/63297-h.htm","application/epub+zip":"https://www.gutenberg.org/ebooks/63297.epub3.images","application/x-mobipocket-ebook":"https://www.gutenberg.org/ebooks/63297.kf8.images","text/plain; charset=us-ascii":"https://www.gutenberg.org/ebooks/63297.txt.utf-8","text/plain; charset=utf-8":"https://www.gutenberg.org/files/63297/63297-0.txt","application/rdf+xml":"https://www.gutenberg.org/ebooks/63297.rdf","image/jpeg":"https://www.gutenberg.org/cache/epub/63297/pg63297.cover.medium.jpg","application/octet-stream":"https://www.gutenberg.org/cache/epub/63297/pg63297-h.zip"},"download_count":34},{"id":63373,"title":"Rain and roses","authors":[{"name":"Henshall, Jeannette Fraser","birth_year":null,"death_year":null}],"translators":[],"subjects":["Poetry"],"bookshelves":[],"languages":["en"],"copyright":false,"media_type":"Text","formats":{"text/html":"https://www.gutenberg.org/ebooks/63373.html.images","text/html; charset=utf-8":"https://www.gutenberg.org/files/63373/63373-h/63373-h.htm","application/epub+zip":"https://www.gutenberg.org/ebooks/63373.epub3.images","application/x-mobipocket-ebook":"https://www.gutenberg.org/ebooks/63373.kf8.images","text/plain; charset=us-ascii":"https://www.gutenberg.org/ebooks/63373.txt.utf-8","text/plain; charset=utf-8":"https://www.gutenberg.org/files/63373/63373-0.txt","application/rdf+xml":"https://www.gutenberg.org/ebooks/63373.rdf","image/jpeg":"https://www.gutenberg.org/cache/epub/63373/pg63373.cover.medium.jpg","application/octet-stream":"https://www.gutenberg.org/cache/epub/63373/pg63373-h.zip"},"download_count":34},{"id":63374,"title":"Confessions of a Railroad Signalman","authors":[{"name":"Fagan, James O. (James Octavius)","birth_year":1859,"death_year":null}],"translators":[],"subjects":["Railroad accidents","Railroads","Railroads -- United States -- Employees"],"bookshelves":[],"languages":["en"],"copyright":false,"media_type":"Text","formats":{"text/html":"https://www.gutenberg.org/ebooks/63374.html.images","application/epub+zip":"https://www.gutenberg.org/ebooks/63374.epub3.images","application/x-mobipocket-ebook":"https://www.gutenberg.org/ebooks/63374.kf8.images","text/plain; charset=us-ascii":"https://www.gutenberg.org/ebooks/63374.txt.utf-8","text/plain; charset=utf-8":"https://www.gutenberg.org/files/63374/63374-0.txt","application/rdf+xml":"https://www.gutenberg.org/ebooks/63374.rdf","image/jpeg":"https://www.gutenberg.org/cache/epub/63374/pg63374.cover.medium.jpg","application/octet-stream":"https://www.gutenberg.org/cache/epub/63374/pg63374-h.zip"},"download_count":34},{"id":63382,"title":"The Attack on the Mill, and Other Sketches of War","authors":[{"name":"Zola, Émile","birth_year":1840,"death_year":1902}],"translators":[],"subjects":["War stories"],"bookshelves":[],"languages":["en"],"copyright":false,"media_type":"Text","formats":{"text/html":"https://www.gutenberg.org/ebooks/63382.html.images","application/epub+zip":"https://www.gutenberg.org/ebooks/63382.epub3.images","application/x-mobipocket-ebook":"https://www.gutenberg.org/ebooks/63382.kf8.images","text/plain; charset=us-ascii":"https://www.gutenberg.org/ebooks/63382.txt.utf-8","text/plain; charset=utf-8":"https://www.gutenberg.org/files/63382/63382-0.txt","application/rdf+xml":"https://www.gutenberg.org/ebooks/63382.rdf","image/jpeg":"https://www.gutenberg.org/cache/epub/63382/pg63382.cover.medium.jpg","application/octet-stream":"https://www.gutenberg.org/cache/epub/63382/pg63382-h.zip"},"download_count":34},{"id":63449,"title":"The Story of the Bank of England: (A History of English Banking, and a Sketch of the Money Market)","authors":[{"name":"Warren, Henry","birth_year":null,"death_year":null}],"translators":[],"subjects":["Bank of England -- History","Banks and banking -- England"],"bookshelves":[],"languages":["en"],"copyright":false,"media_type":"Text","formats":{"text/html":"https://www.gutenberg.org/ebooks/63449.html.images","text/html; charset=utf-8":"https://www.gutenberg.org/files/63449/63449-h/63449-h.htm","application/epub+zip":"https://www.gutenberg.org/ebooks/63449.epub3.images","application/x-mobipocket-ebook":"https://www.gutenberg.org/ebooks/63449.kf8.images","text/plain; charset=us-ascii":"https://www.gutenberg.org/ebooks/63449.txt.utf-8","text/plain; charset=utf-8":"https://www.gutenberg.org/files/63449/63449-0.txt","application/rdf+xml":"https://www.gutenberg.org/ebooks/63449.rdf","image/jpeg":"https://www.gutenberg.org/cache/epub/63449/pg63449.cover.medium.jpg","application/octet-stream":"https://www.gutenberg.org/cache/epub/63449/pg63449-h.zip"},"download_count":34},{"id":63458,"title":"Pussy-Cat Town","authors":[{"name":"Taggart, Marion Ames","birth_year":1866,"death_year":1945}],"translators":[],"subjects":["Cats -- Juvenile fiction"],"bookshelves":[],"languages":["en"],"copyright":false,"media_type":"Text","formats":{"text/html":"https://www.gutenberg.org/ebooks/63458.html.images","application/epub+zip":"https://www.gutenberg.org/ebooks/63458.epub3.images","application/x-mobipocket-ebook":"https://www.gutenberg.org/ebooks/63458.kf8.images","text/plain; charset=us-ascii":"https://www.gutenberg.org/ebooks/63458.txt.utf-8","text/plain; charset=utf-8":"https://www.gutenberg.org/files/63458/63458-0.txt","application/rdf+xml":"https://www.gutenberg.org/ebooks/63458.rdf","image/jpeg":"https://www.gutenberg.org/cache/epub/63458/pg63458.cover.medium.jpg","application/octet-stream":"https://www.gutenberg.org/cache/epub/63458/pg63458-h.zip"},"download_count":34},{"id":63490,"title":"The Altar of Freedom","authors":[{"name":"Rinehart, Mary Roberts","birth_year":1876,"death_year":1958}],"translators":[],"subjects":["Draft","United States -- Defenses"],"bookshelves":[],"languages":["en"],"copyright":false,"media_type":"Text","formats":{"text/html":"https://www.gutenberg.org/ebooks/63490.html.images","text/html; charset=utf-8":"https://www.gutenberg.org/files/63490/63490-h/63490-h.htm","application/epub+zip":"https://www.gutenberg.org/ebooks/63490.epub3.images","application/x-mobipocket-ebook":"https://www.gutenberg.org/ebooks/63490.kf8.images","text/plain; charset=us-ascii":"https://www.gutenberg.org/ebooks/63490.txt.utf-8","text/plain; charset=utf-8":"https://www.gutenberg.org/files/63490/63490-0.txt","application/rdf+xml":"https://www.gutenberg.org/ebooks/63490.rdf","image/jpeg":"https://www.gutenberg.org/cache/epub/63490/pg63490.cover.medium.jpg","application/octet-stream":"https://www.gutenberg.org/cache/epub/63490/pg63490-h.zip"},"download_count":34}]}